hydrogels/__init__.py
hydrogels/_version.py
hydrogels/functions.cpython-36m-darwin.so
hydrogels/potentials.cpython-36m-darwin.so
hydrogels/generators/__init__.py
hydrogels/generators/polymers.py
hydrogels/generators/gels/__init__.py
hydrogels/generators/gels/core.py
hydrogels/generators/gels/generic.py
hydrogels/reactions/__init__.py
hydrogels/reactions/spatial.py
hydrogels/reactions/structural.py
hydrogels/systems/__init__.py
hydrogels/systems/degradation.py
hydrogels/theory/__init__.py
hydrogels/theory/models/__init__.py
hydrogels/theory/models/utils.py
hydrogels/theory/models/analytical/__init__.py
hydrogels/theory/models/integrator/__init__.py
hydrogels/theory/models/integrator/engine.py
hydrogels/theory/models/simulations/__init__.py
hydrogels/theory/models/simulations/constant_density.py
hydrogels/theory/models/simulations/lennard_jones.py
hydrogels/trajectory/__init__.py
hydrogels/trajectory/core.py
hydrogels/trajectory/lammps.py
hydrogels/trajectory/ovito.py
hydrogels/utils/__init__.py
hydrogels/utils/simulation.py
hydrogels/utils/system.py
hydrogels/utils/topology.py
hydrogels/utils/io/__init__.py
hydrogels/utils/io/_core.py
hydrogels/utils/io/_hydrogels.py
hydrogels/utils/io/_lammps.py
hydrogels/utils/io/_reader.py
hydrogels-1.1.1.dist-info/LICENSE
hydrogels-1.1.1.dist-info/METADATA
hydrogels-1.1.1.dist-info/WHEEL
hydrogels-1.1.1.dist-info/top_level.txt
hydrogels-1.1.1.dist-info/RECORD
