Metadata-Version: 2.1
Name: hydrogels
Version: 1.1.1
Summary: Package for creating and analysing hydrogels in ReaDDy
Home-page: https://github.com/debeshmandal/hydrogels
Author: Debesh Mandal
License: UNKNOWN
Platform: UNKNOWN
Classifier: Programming Language :: Python :: 3
Classifier: License :: OSI Approved :: MIT License
Classifier: Operating System :: POSIX
Requires-Python: >=3.6
License-File: LICENSE
